AUTHORS
LICENCE
MANIFEST.in
README.rst
setup.py
django_multiuploader.egg-info/PKG-INFO
django_multiuploader.egg-info/SOURCES.txt
django_multiuploader.egg-info/dependency_links.txt
django_multiuploader.egg-info/not-zip-safe
django_multiuploader.egg-info/requires.txt
django_multiuploader.egg-info/top_level.txt
multiuploader/__init__.py
multiuploader/admin.py
multiuploader/context_processors.py
multiuploader/default_settings.py
multiuploader/forms.py
multiuploader/models.py
multiuploader/tests.py
multiuploader/urls.py
multiuploader/utils.py
multiuploader/views.py
multiuploader/locale/ru/LC_MESSAGES/django.mo
multiuploader/locale/ru/LC_MESSAGES/django.po
multiuploader/management/__init__.py
multiuploader/management/commands/__init__.py
multiuploader/management/commands/clean_uploads.py
multiuploader/management/commands/clear_sorlthumbnails.py
multiuploader/migrations/0001_initial.py
multiuploader/migrations/__init__.py
multiuploader/static/multiuploader/scripts/collectfiles.js
multiuploader/static/multiuploader/scripts/jquery-ui.min.js
multiuploader/static/multiuploader/scripts/jquery.fileupload-ui.js
multiuploader/static/multiuploader/scripts/jquery.fileupload.js
multiuploader/static/multiuploader/scripts/jquery.iframe-transport.js
multiuploader/static/multiuploader/scripts/jquery.min.js
multiuploader/static/multiuploader/scripts/jquery.tmpl.min.js
multiuploader/static/multiuploader/site_graphics/pbar-ani.gif
multiuploader/static/multiuploader/styles/jquery-ui.css
multiuploader/static/multiuploader/styles/jquery.fileupload-ui.css
multiuploader/static/multiuploader/styles/images/ui-bg_flat_0_aaaaaa_40x100.png
multiuploader/static/multiuploader/styles/images/ui-bg_flat_75_ffffff_40x100.png
multiuploader/static/multiuploader/styles/images/ui-bg_glass_55_fbf9ee_1x400.png
multiuploader/static/multiuploader/styles/images/ui-bg_glass_65_ffffff_1x400.png
multiuploader/static/multiuploader/styles/images/ui-bg_glass_75_dadada_1x400.png
multiuploader/static/multiuploader/styles/images/ui-bg_glass_75_e6e6e6_1x400.png
multiuploader/static/multiuploader/styles/images/ui-bg_glass_95_fef1ec_1x400.png
multiuploader/static/multiuploader/styles/images/ui-bg_highlight-soft_75_cccccc_1x100.png
