Metadata-Version: 1.0
Name: django-multiuploader
Version: 0.2.4
Summary: Adds jQuery dynamic form for uploading multiple files
Home-page: http://openite.com/ru/store/item/django-multiuploader.html
Author: Sinitsin Vladimir and Ivanov Vitaly
Author-email: vs@llc.ac; vit@nlstar.com
License: BSD licence, see LICENCE.txt
Platform: UNKNOWN
